slurm_gpustat/slurm_gpustat.py
slurm_gpustat-0.0.15.dist-info/METADATA
slurm_gpustat-0.0.15.dist-info/WHEEL
slurm_gpustat-0.0.15.dist-info/entry_points.txt
slurm_gpustat-0.0.15.dist-info/top_level.txt
slurm_gpustat-0.0.15.dist-info/RECORD
